{
  "id": 10000044,
  "name": "Xinyan",
  "title": "Blazing Riff",
  "description": "Liyue's sole rock 'n' roll musician. She rebels against ossified prejudices using her music and passionate singing.",
  "weaponType": "WEAPON_CLAYMORE",
  "weaponText": "Claymore",
  "bodyType": "BODY_GIRL",
  "gender": "Female",
  "qualityType": "QUALITY_PURPLE",
  "rarity": 4,
  "birthdaymmdd": "10/16",
  "birthday": "October 16",
  "elementType": "ELEMENT_PYRO",
  "elementText": "Pyro",
  "affiliation": "\"The Red Strings\"",
  "associationType": "ASSOC_LIYUE",
  "region": "Liyue",
  "substatType": "FIGHT_PROP_ATTACK_PERCENT",
  "substatText": "ATK",
  "constellation": "Fila Ignium",
  "cv": {
    "english": "Laura Stahl",
    "chinese": "王雅欣",
    "japanese": "たかはし智秋",
    "korean": "Kim Chae-ha"
  },
  "costs": {
    "ascend1": [
      {
        "id": 202,
        "name": "Mora",
        "count": 20000
      },
      {
        "id": 104111,
        "name": "Agnidus Agate Sliver",
        "count": 1
      },
      {
        "id": 100034,
        "name": "Violetgrass",
        "count": 3
      },
      {
        "id": 112035,
        "name": "Treasure Hoarder Insignia",
        "count": 3
      }
    ],
    "ascend2": [
      {
        "id": 202,
        "name": "Mora",
        "count": 40000
      },
      {
        "id": 104112,
        "name": "Agnidus Agate Fragment",
        "count": 3
      },
      {
        "id": 113011,
        "name": "Everflame Seed",
        "count": 2
      },
      {
        "id": 100034,
        "name": "Violetgrass",
        "count": 10
      },
      {
        "id": 112035,
        "name": "Treasure Hoarder Insignia",
        "count": 15
      }
    ],
    "ascend3": [
      {
        "id": 202,
        "name": "Mora",
        "count": 60000
      },
      {
        "id": 104112,
        "name": "Agnidus Agate Fragment",
        "count": 6
      },
      {
        "id": 113011,
        "name": "Everflame Seed",
        "count": 4
      },
      {
        "id": 100034,
        "name": "Violetgrass",
        "count": 20
      },
      {
        "id": 112036,
        "name": "Silver Raven Insignia",
        "count": 12
      }
    ],
    "ascend4": [
      {
        "id": 202,
        "name": "Mora",
        "count": 80000
      },
      {
        "id": 104113,
        "name": "Agnidus Agate Chunk",
        "count": 3
      },
      {
        "id": 113011,
        "name": "Everflame Seed",
        "count": 8
      },
      {
        "id": 100034,
        "name": "Violetgrass",
        "count": 30
      },
      {
        "id": 112036,
        "name": "Silver Raven Insignia",
        "count": 18
      }
    ],
    "ascend5": [
      {
        "id": 202,
        "name": "Mora",
        "count": 100000
      },
      {
        "id": 104113,
        "name": "Agnidus Agate Chunk",
        "count": 6
      },
      {
        "id": 113011,
        "name": "Everflame Seed",
        "count": 12
      },
      {
        "id": 100034,
        "name": "Violetgrass",
        "count": 45
      },
      {
        "id": 112037,
        "name": "Golden Raven Insignia",
        "count": 12
      }
    ],
    "ascend6": [
      {
        "id": 202,
        "name": "Mora",
        "count": 120000
      },
      {
        "id": 104114,
        "name": "Agnidus Agate Gemstone",
        "count": 6
      },
      {
        "id": 113011,
        "name": "Everflame Seed",
        "count": 20
      },
      {
        "id": 100034,
        "name": "Violetgrass",
        "count": 60
      },
      {
        "id": 112037,
        "name": "Golden Raven Insignia",
        "count": 24
      }
    ]
  },
  "images": {
    "card": "https://static.wikia.nocookie.net/gensin-impact/images/4/4c/Character_Xinyan_Card.jpeg",
    "portrait": "https://static.wikia.nocookie.net/gensin-impact/images/c/c8/Character_Xinyan_Portrait.png",
    "cover1": "https://act-webstatic.hoyoverse.com/upload/contentweb/2022/07/22/3deca8e73a03e779087b74ebeac883cb_7694328369896454033.png",
    "cover2": "https://webstatic.hoyoverse.com/upload/uploadstatic/contentweb/20201125/2020112516125848571.png",
    "hoyolab-avatar": "https://img-os-static.hoyolab.com/communityWeb/upload/1a30faffb4b122f778b1ab4c7c39d6bf.png",
    "filename_icon": "UI_AvatarIcon_Xinyan",
    "filename_iconCard": "UI_AvatarIcon_Xinyan_Card",
    "filename_sideIcon": "UI_AvatarIcon_Side_Xinyan",
    "filename_gachaSplash": "UI_Gacha_AvatarImg_Xinyan",
    "filename_gachaSlice": "UI_Gacha_AvatarIcon_Xinyan",
    "mihoyo_icon": "https://upload-os-bbs.mihoyo.com/game_record/genshin/character_icon/UI_AvatarIcon_Xinyan.png",
    "mihoyo_sideIcon": "https://upload-os-bbs.mihoyo.com/game_record/genshin/character_side_icon/UI_AvatarIcon_Side_Xinyan.png"
  },
  "url": {
    "fandom": "https://genshin-impact.fandom.com/wiki/Xinyan"
  },
  "version": "1.1"
}