{
  "1": {
    "level": 1,
    "ascension": 0,
    "hp": 775.02234,
    "attack": 14.2464,
    "defense": 58.94175,
    "specialized": 0
  },
  "2": {
    "level": 2,
    "ascension": 0,
    "hp": 839.34919422,
    "attack": 15.428851199999999,
    "defense": 63.83391525,
    "specialized": 0
  },
  "3": {
    "level": 3,
    "ascension": 0,
    "hp": 902.9010261,
    "attack": 16.597056,
    "defense": 68.66713875,
    "specialized": 0
  },
  "4": {
    "level": 4,
    "ascension": 0,
    "hp": 967.2278803199999,
    "attack": 17.779507199999998,
    "defense": 73.559304,
    "specialized": 0
  },
  "5": {
    "level": 5,
    "ascension": 0,
    "hp": 1030.7797122,
    "attack": 18.947712,
    "defense": 78.3925275,
    "specialized": 0
  },
  "6": {
    "level": 6,
    "ascension": 0,
    "hp": 1095.10656642,
    "attack": 20.1301632,
    "defense": 83.28469275,
    "specialized": 0
  },
  "7": {
    "level": 7,
    "ascension": 0,
    "hp": 1158.6583983,
    "attack": 21.298368,
    "defense": 88.11791625000001,
    "specialized": 0
  },
  "8": {
    "level": 8,
    "ascension": 0,
    "hp": 1222.9852525200001,
    "attack": 22.4808192,
    "defense": 93.0100815,
    "specialized": 0
  },
  "9": {
    "level": 9,
    "ascension": 0,
    "hp": 1287.31210674,
    "attack": 23.6632704,
    "defense": 97.90224675,
    "specialized": 0
  },
  "10": {
    "level": 10,
    "ascension": 0,
    "hp": 1350.86393862,
    "attack": 24.8314752,
    "defense": 102.73547025,
    "specialized": 0
  },
  "11": {
    "level": 11,
    "ascension": 0,
    "hp": 1415.19079284,
    "attack": 26.0139264,
    "defense": 107.6276355,
    "specialized": 0
  },
  "12": {
    "level": 12,
    "ascension": 0,
    "hp": 1478.7426247199999,
    "attack": 27.182131199999997,
    "defense": 112.460859,
    "specialized": 0
  },
  "13": {
    "level": 13,
    "ascension": 0,
    "hp": 1543.06947894,
    "attack": 28.3645824,
    "defense": 117.35302425,
    "specialized": 0
  },
  "14": {
    "level": 14,
    "ascension": 0,
    "hp": 1606.62131082,
    "attack": 29.532787199999998,
    "defense": 122.18624774999999,
    "specialized": 0
  },
  "15": {
    "level": 15,
    "ascension": 0,
    "hp": 1670.94816504,
    "attack": 30.7152384,
    "defense": 127.07841300000001,
    "specialized": 0
  },
  "16": {
    "level": 16,
    "ascension": 0,
    "hp": 1735.27501926,
    "attack": 31.897689599999996,
    "defense": 131.97057825,
    "specialized": 0
  },
  "17": {
    "level": 17,
    "ascension": 0,
    "hp": 1798.8268511400001,
    "attack": 33.065894400000005,
    "defense": 136.80380175000002,
    "specialized": 0
  },
  "18": {
    "level": 18,
    "ascension": 0,
    "hp": 1863.15370536,
    "attack": 34.2483456,
    "defense": 141.695967,
    "specialized": 0
  },
  "19": {
    "level": 19,
    "ascension": 0,
    "hp": 1926.7055372400002,
    "attack": 35.4165504,
    "defense": 146.5291905,
    "specialized": 0
  },
  "20": {
    "level": 20,
    "ascension": 0,
    "hp": 1991.0323914599999,
    "attack": 36.5990016,
    "defense": 151.42135575,
    "specialized": 0
  },
  "21": {
    "level": 21,
    "ascension": 1,
    "hp": 2633.56562334,
    "attack": 48.4102464,
    "defense": 200.28707924999998,
    "specialized": 0
  },
  "22": {
    "level": 22,
    "ascension": 1,
    "hp": 2697.89247756,
    "attack": 49.5926976,
    "defense": 205.17924449999998,
    "specialized": 0
  },
  "23": {
    "level": 23,
    "ascension": 1,
    "hp": 2762.21933178,
    "attack": 50.775148800000004,
    "defense": 210.07140975000002,
    "specialized": 0
  },
  "24": {
    "level": 24,
    "ascension": 1,
    "hp": 2825.77116366,
    "attack": 51.943353599999995,
    "defense": 214.90463325,
    "specialized": 0
  },
  "25": {
    "level": 25,
    "ascension": 1,
    "hp": 2890.09801788,
    "attack": 53.1258048,
    "defense": 219.7967985,
    "specialized": 0
  },
  "26": {
    "level": 26,
    "ascension": 1,
    "hp": 2953.64984976,
    "attack": 54.294009599999995,
    "defense": 224.630022,
    "specialized": 0
  },
  "27": {
    "level": 27,
    "ascension": 1,
    "hp": 3017.97670398,
    "attack": 55.4764608,
    "defense": 229.52218724999997,
    "specialized": 0
  },
  "28": {
    "level": 28,
    "ascension": 1,
    "hp": 3081.52853586,
    "attack": 56.644665599999996,
    "defense": 234.35541075,
    "specialized": 0
  },
  "29": {
    "level": 29,
    "ascension": 1,
    "hp": 3145.85539008,
    "attack": 57.82711679999999,
    "defense": 239.24757599999998,
    "specialized": 0
  },
  "30": {
    "level": 30,
    "ascension": 1,
    "hp": 3209.4072219600002,
    "attack": 58.9953216,
    "defense": 244.0807995,
    "specialized": 0
  },
  "31": {
    "level": 31,
    "ascension": 1,
    "hp": 3273.73407618,
    "attack": 60.17777279999999,
    "defense": 248.97296475,
    "specialized": 0
  },
  "32": {
    "level": 32,
    "ascension": 1,
    "hp": 3338.0609304,
    "attack": 61.360223999999995,
    "defense": 253.86513,
    "specialized": 0
  },
  "33": {
    "level": 33,
    "ascension": 1,
    "hp": 3401.61276228,
    "attack": 62.52842879999999,
    "defense": 258.6983535,
    "specialized": 0
  },
  "34": {
    "level": 34,
    "ascension": 1,
    "hp": 3465.9396165000003,
    "attack": 63.710879999999996,
    "defense": 263.59051875,
    "specialized": 0
  },
  "35": {
    "level": 35,
    "ascension": 1,
    "hp": 3529.49144838,
    "attack": 64.87908479999999,
    "defense": 268.42374225000003,
    "specialized": 0
  },
  "36": {
    "level": 36,
    "ascension": 1,
    "hp": 3593.8183026,
    "attack": 66.06153599999999,
    "defense": 273.3159075,
    "specialized": 0
  },
  "37": {
    "level": 37,
    "ascension": 1,
    "hp": 3657.37013448,
    "attack": 67.2297408,
    "defense": 278.149131,
    "specialized": 0
  },
  "38": {
    "level": 38,
    "ascension": 1,
    "hp": 3721.6969887,
    "attack": 68.41219199999999,
    "defense": 283.04129624999996,
    "specialized": 0
  },
  "39": {
    "level": 39,
    "ascension": 1,
    "hp": 3786.02384292,
    "attack": 69.5946432,
    "defense": 287.9334615,
    "specialized": 0
  },
  "40": {
    "level": 40,
    "ascension": 1,
    "hp": 3849.5756748,
    "attack": 70.76284799999999,
    "defense": 292.76668499999994,
    "specialized": 0
  },
  "41": {
    "level": 41,
    "ascension": 2,
    "hp": 4325.28397902,
    "attack": 79.5074592,
    "defense": 328.94510025,
    "specialized": 0.06
  },
  "42": {
    "level": 42,
    "ascension": 2,
    "hp": 4388.8358109,
    "attack": 80.675664,
    "defense": 333.77832375,
    "specialized": 0.06
  },
  "43": {
    "level": 43,
    "ascension": 2,
    "hp": 4453.16266512,
    "attack": 81.8581152,
    "defense": 338.670489,
    "specialized": 0.06
  },
  "44": {
    "level": 44,
    "ascension": 2,
    "hp": 4516.714497,
    "attack": 83.02632,
    "defense": 343.5037125,
    "specialized": 0.06
  },
  "45": {
    "level": 45,
    "ascension": 2,
    "hp": 4581.041351219999,
    "attack": 84.2087712,
    "defense": 348.39587774999995,
    "specialized": 0.06
  },
  "46": {
    "level": 46,
    "ascension": 2,
    "hp": 4645.36820544,
    "attack": 85.3912224,
    "defense": 353.288043,
    "specialized": 0.06
  },
  "47": {
    "level": 47,
    "ascension": 2,
    "hp": 4708.92003732,
    "attack": 86.5594272,
    "defense": 358.12126650000005,
    "specialized": 0.06
  },
  "48": {
    "level": 48,
    "ascension": 2,
    "hp": 4773.24689154,
    "attack": 87.7418784,
    "defense": 363.01343175,
    "specialized": 0.06
  },
  "49": {
    "level": 49,
    "ascension": 2,
    "hp": 4836.79872342,
    "attack": 88.9100832,
    "defense": 367.84665525,
    "specialized": 0.06
  },
  "50": {
    "level": 50,
    "ascension": 2,
    "hp": 4901.12557764,
    "attack": 90.0925344,
    "defense": 372.7388205,
    "specialized": 0.06
  },
  "51": {
    "level": 51,
    "ascension": 3,
    "hp": 5513.18615952,
    "attack": 101.3436192,
    "defense": 419.287044,
    "specialized": 0.12
  },
  "52": {
    "level": 52,
    "ascension": 3,
    "hp": 5577.51301374,
    "attack": 102.52607040000001,
    "defense": 424.17920925,
    "specialized": 0.12
  },
  "53": {
    "level": 53,
    "ascension": 3,
    "hp": 5641.8398679599995,
    "attack": 103.70852159999998,
    "defense": 429.0713745,
    "specialized": 0.12
  },
  "54": {
    "level": 54,
    "ascension": 3,
    "hp": 5705.39169984,
    "attack": 104.8767264,
    "defense": 433.904598,
    "specialized": 0.12
  },
  "55": {
    "level": 55,
    "ascension": 3,
    "hp": 5769.71855406,
    "attack": 106.0591776,
    "defense": 438.79676324999997,
    "specialized": 0.12
  },
  "56": {
    "level": 56,
    "ascension": 3,
    "hp": 5833.270385940001,
    "attack": 107.22738240000001,
    "defense": 443.62998675,
    "specialized": 0.12
  },
  "57": {
    "level": 57,
    "ascension": 3,
    "hp": 5897.597240159999,
    "attack": 108.40983359999998,
    "defense": 448.52215199999995,
    "specialized": 0.12
  },
  "58": {
    "level": 58,
    "ascension": 3,
    "hp": 5961.14907204,
    "attack": 109.5780384,
    "defense": 453.35537550000004,
    "specialized": 0.12
  },
  "59": {
    "level": 59,
    "ascension": 3,
    "hp": 6025.47592626,
    "attack": 110.7604896,
    "defense": 458.24754075,
    "specialized": 0.12
  },
  "60": {
    "level": 60,
    "ascension": 3,
    "hp": 6089.80278048,
    "attack": 111.9429408,
    "defense": 463.139706,
    "specialized": 0.12
  },
  "61": {
    "level": 61,
    "ascension": 4,
    "hp": 6564.736012359999,
    "attack": 120.67330559999999,
    "defense": 499.25917949999996,
    "specialized": 0.12
  },
  "62": {
    "level": 62,
    "ascension": 4,
    "hp": 6629.0628665799995,
    "attack": 121.8557568,
    "defense": 504.15134474999996,
    "specialized": 0.12
  },
  "63": {
    "level": 63,
    "ascension": 4,
    "hp": 6692.614698459999,
    "attack": 123.02396159999999,
    "defense": 508.98456825,
    "specialized": 0.12
  },
  "64": {
    "level": 64,
    "ascension": 4,
    "hp": 6756.941552679999,
    "attack": 124.2064128,
    "defense": 513.8767335,
    "specialized": 0.12
  },
  "65": {
    "level": 65,
    "ascension": 4,
    "hp": 6820.49338456,
    "attack": 125.3746176,
    "defense": 518.709957,
    "specialized": 0.12
  },
  "66": {
    "level": 66,
    "ascension": 4,
    "hp": 6884.820238779999,
    "attack": 126.5570688,
    "defense": 523.60212225,
    "specialized": 0.12
  },
  "67": {
    "level": 67,
    "ascension": 4,
    "hp": 6949.147093,
    "attack": 127.73952,
    "defense": 528.4942874999999,
    "specialized": 0.12
  },
  "68": {
    "level": 68,
    "ascension": 4,
    "hp": 7012.69892488,
    "attack": 128.90772479999998,
    "defense": 533.327511,
    "specialized": 0.12
  },
  "69": {
    "level": 69,
    "ascension": 4,
    "hp": 7077.025779099999,
    "attack": 130.09017599999999,
    "defense": 538.21967625,
    "specialized": 0.12
  },
  "70": {
    "level": 70,
    "ascension": 4,
    "hp": 7140.57761098,
    "attack": 131.2583808,
    "defense": 543.05289975,
    "specialized": 0.12
  },
  "71": {
    "level": 71,
    "ascension": 5,
    "hp": 7616.285965200001,
    "attack": 140.002992,
    "defense": 579.231315,
    "specialized": 0.18
  },
  "72": {
    "level": 72,
    "ascension": 5,
    "hp": 7679.83779708,
    "attack": 141.1711968,
    "defense": 584.0645385,
    "specialized": 0.18
  },
  "73": {
    "level": 73,
    "ascension": 5,
    "hp": 7744.1646513000005,
    "attack": 142.353648,
    "defense": 588.95670375,
    "specialized": 0.18
  },
  "74": {
    "level": 74,
    "ascension": 5,
    "hp": 7808.49150552,
    "attack": 143.5360992,
    "defense": 593.8488689999999,
    "specialized": 0.18
  },
  "75": {
    "level": 75,
    "ascension": 5,
    "hp": 7872.0433374,
    "attack": 144.704304,
    "defense": 598.6820925,
    "specialized": 0.18
  },
  "76": {
    "level": 76,
    "ascension": 5,
    "hp": 7936.37019162,
    "attack": 145.88675519999998,
    "defense": 603.57425775,
    "specialized": 0.18
  },
  "77": {
    "level": 77,
    "ascension": 5,
    "hp": 7999.9220235,
    "attack": 147.05496,
    "defense": 608.40748125,
    "specialized": 0.18
  },
  "78": {
    "level": 78,
    "ascension": 5,
    "hp": 8064.24887772,
    "attack": 148.2374112,
    "defense": 613.2996464999999,
    "specialized": 0.18
  },
  "79": {
    "level": 79,
    "ascension": 5,
    "hp": 8127.8007096,
    "attack": 149.405616,
    "defense": 618.13287,
    "specialized": 0.18
  },
  "80": {
    "level": 80,
    "ascension": 5,
    "hp": 8192.127563819999,
    "attack": 150.58806719999998,
    "defense": 623.02503525,
    "specialized": 0.18
  },
  "81": {
    "level": 81,
    "ascension": 6,
    "hp": 8667.83591804,
    "attack": 159.3326784,
    "defense": 659.2034505,
    "specialized": 0.24
  },
  "82": {
    "level": 82,
    "ascension": 6,
    "hp": 8731.387749919999,
    "attack": 160.50088319999998,
    "defense": 664.036674,
    "specialized": 0.24
  },
  "83": {
    "level": 83,
    "ascension": 6,
    "hp": 8795.71460414,
    "attack": 161.68333439999998,
    "defense": 668.92883925,
    "specialized": 0.24
  },
  "84": {
    "level": 84,
    "ascension": 6,
    "hp": 8859.26643602,
    "attack": 162.8515392,
    "defense": 673.76206275,
    "specialized": 0.24
  },
  "85": {
    "level": 85,
    "ascension": 6,
    "hp": 8923.59329024,
    "attack": 164.0339904,
    "defense": 678.654228,
    "specialized": 0.24
  },
  "86": {
    "level": 86,
    "ascension": 6,
    "hp": 8987.14512212,
    "attack": 165.2021952,
    "defense": 683.4874515,
    "specialized": 0.24
  },
  "87": {
    "level": 87,
    "ascension": 6,
    "hp": 9051.47197634,
    "attack": 166.3846464,
    "defense": 688.3796167500001,
    "specialized": 0.24
  },
  "88": {
    "level": 88,
    "ascension": 6,
    "hp": 9115.02380822,
    "attack": 167.5528512,
    "defense": 693.21284025,
    "specialized": 0.24
  },
  "89": {
    "level": 89,
    "ascension": 6,
    "hp": 9179.35066244,
    "attack": 168.7353024,
    "defense": 698.1050055000001,
    "specialized": 0.24
  },
  "90": {
    "level": 90,
    "ascension": 6,
    "hp": 9243.67751666,
    "attack": 169.9177536,
    "defense": 702.99717075,
    "specialized": 0.24
  },
  "20+": {
    "level": 20,
    "ascension": 1,
    "hp": 2570.01379146,
    "attack": 47.2420416,
    "defense": 195.45385575,
    "specialized": 0
  },
  "40+": {
    "level": 40,
    "ascension": 2,
    "hp": 4260.957124799999,
    "attack": 78.325008,
    "defense": 324.05293499999993,
    "specialized": 0.06
  },
  "50+": {
    "level": 50,
    "ascension": 3,
    "hp": 5449.63432764,
    "attack": 100.1754144,
    "defense": 414.4538205,
    "specialized": 0.12
  },
  "60+": {
    "level": 60,
    "ascension": 4,
    "hp": 6501.18418048,
    "attack": 119.5051008,
    "defense": 494.425956,
    "specialized": 0.12
  },
  "70+": {
    "level": 70,
    "ascension": 5,
    "hp": 7551.95911098,
    "attack": 138.8205408,
    "defense": 574.3391497499999,
    "specialized": 0.18
  },
  "80+": {
    "level": 80,
    "ascension": 6,
    "hp": 8603.50906382,
    "attack": 158.1502272,
    "defense": 654.31128525,
    "specialized": 0.24
  }
}